odoo/addons/purchase_request_tier_validation/README.rst
odoo/addons/purchase_request_tier_validation/__init__.py
odoo/addons/purchase_request_tier_validation/__manifest__.py
odoo/addons/purchase_request_tier_validation/demo/tier_definition.xml
odoo/addons/purchase_request_tier_validation/i18n/es.po
odoo/addons/purchase_request_tier_validation/i18n/es_EC.po
odoo/addons/purchase_request_tier_validation/i18n/it.po
odoo/addons/purchase_request_tier_validation/i18n/nl_NL.po
odoo/addons/purchase_request_tier_validation/i18n/pt_BR.po
odoo/addons/purchase_request_tier_validation/i18n/purchase_request_tier_validation.pot
odoo/addons/purchase_request_tier_validation/i18n/tr.po
odoo/addons/purchase_request_tier_validation/i18n/zh_CN.po
odoo/addons/purchase_request_tier_validation/models/__init__.py
odoo/addons/purchase_request_tier_validation/models/purchase_request.py
odoo/addons/purchase_request_tier_validation/models/tier_definition.py
odoo/addons/purchase_request_tier_validation/readme/CONFIGURE.md
odoo/addons/purchase_request_tier_validation/readme/CONTRIBUTORS.md
odoo/addons/purchase_request_tier_validation/readme/CREDITS.md
odoo/addons/purchase_request_tier_validation/readme/DESCRIPTION.md
odoo/addons/purchase_request_tier_validation/readme/INSTALL.md
odoo/addons/purchase_request_tier_validation/readme/USAGE.md
odoo/addons/purchase_request_tier_validation/static/description/icon.png
odoo/addons/purchase_request_tier_validation/static/description/index.html
odoo/addons/purchase_request_tier_validation/tests/__init__.py
odoo/addons/purchase_request_tier_validation/tests/test_purchase_request_tier_validation.py
odoo/addons/purchase_request_tier_validation/views/purchase_request_view.xml
odoo_addon_purchase_request_tier_validation-18.0.1.1.1.3.dist-info/METADATA
odoo_addon_purchase_request_tier_validation-18.0.1.1.1.3.dist-info/WHEEL
odoo_addon_purchase_request_tier_validation-18.0.1.1.1.3.dist-info/top_level.txt
odoo_addon_purchase_request_tier_validation-18.0.1.1.1.3.dist-info/RECORD
