Metadata-Version: 2.1
Name: odoo-addon-purchase_request_tier_validation
Version: 18.0.1.1.1.3
Requires-Python: >=3.10
Requires-Dist: odoo-addon-base_tier_validation==18.0.*
Requires-Dist: odoo-addon-purchase_request==18.0.*
Requires-Dist: odoo==18.0.*
Summary: Extends the functionality of Purchase Requests to support a tier validation process.
Home-page: https://github.com/OCA/purchase-workflow
License: AGPL-3
Author: ForgeFlow, Odoo Community Association (OCA)
Author-email: support@odoo-community.org
Classifier: Programming Language :: Python
Classifier: Framework :: Odoo
Classifier: Framework :: Odoo :: 18.0
Classifier: License :: OSI Approved :: GNU Affero General Public License v3
